{"office": "State House", "district": "37.0", "level": "vtd20", "keys": "Join on VTD20 GEOID20 (state+county+vtd id). Built by matching precinct names to VTD20 join keys; optionally uses --vtd20-crosswalk and --vtd20-supplemental-keymap.", "results": {"1306700CH03": {"total_votes": 2, "dem_votes": 2, "rep_votes": 0, "other_votes": 0, "winner_candidate": "Mary Frances Williams", "winner_party": "UNK", "winner_votes": 2, "margin_votes": 2}, "1306700MR2B": {"total_votes": 2458, "dem_votes": 1432, "rep_votes": 1026, "other_votes": 0, "winner_candidate": "Mary Frances Williams", "winner_party": "UNK", "winner_votes": 1432, "margin_votes": 406}, "1306700MR1A": {"total_votes": 1050, "dem_votes": 591, "rep_votes": 459, "other_votes": 0, "winner_candidate": "Mary Frances Williams", "winner_party": "UNK", "winner_votes": 591, "margin_votes": 132}, "1306700MR4A": {"total_votes": 1544, "dem_votes": 490, "rep_votes": 1054, "other_votes": 0, "winner_candidate": "Marites \"\"Tess\"\" Redding", "winner_party": "UNK", "winner_votes": 1054, "margin_votes": 564}, "1306700MR5B": {"total_votes": 1016, "dem_votes": 787, "rep_votes": 229, "other_votes": 0, "winner_candidate": "Mary Frances Williams", "winner_party": "UNK", "winner_votes": 787, "margin_votes": 558}, "1306700MR5A": {"total_votes": 1281, "dem_votes": 797, "rep_votes": 484, "other_votes": 0, "winner_candidate": "Mary Frances Williams", "winner_party": "UNK", "winner_votes": 797, "margin_votes": 313}, "1306700MR2A": {"total_votes": 463, "dem_votes": 218, "rep_votes": 245, "other_votes": 0, "winner_candidate": "Marites \"\"Tess\"\" Redding", "winner_party": "UNK", "winner_votes": 245, "margin_votes": 27}, "1306700MR3A": {"total_votes": 2705, "dem_votes": 1419, "rep_votes": 1286, "other_votes": 0, "winner_candidate": "Mary Frances Williams", "winner_party": "UNK", "winner_votes": 1419, "margin_votes": 133}, "1306700EL04": {"total_votes": 455, "dem_votes": 274, "rep_votes": 181, "other_votes": 0, "winner_candidate": "Mary Frances Williams", "winner_party": "UNK", "winner_votes": 274, "margin_votes": 93}, "1306700EL02": {"total_votes": 1471, "dem_votes": 649, "rep_votes": 822, "other_votes": 0, "winner_candidate": "Marites \"\"Tess\"\" Redding", "winner_party": "UNK", "winner_votes": 822, "margin_votes": 173}, "1306700OR03": {"total_votes": 934, "dem_votes": 662, "rep_votes": 272, "other_votes": 0, "winner_candidate": "Mary Frances Williams", "winner_party": "UNK", "winner_votes": 662, "margin_votes": 390}, "1306700EL01": {"total_votes": 1515, "dem_votes": 1079, "rep_votes": 436, "other_votes": 0, "winner_candidate": "Mary Frances Williams", "winner_party": "UNK", "winner_votes": 1079, "margin_votes": 643}, "1306700MR6B": {"total_votes": 1883, "dem_votes": 1020, "rep_votes": 863, "other_votes": 0, "winner_candidate": "Mary Frances Williams", "winner_party": "UNK", "winner_votes": 1020, "margin_votes": 157}, "1306700MR6A": {"total_votes": 227, "dem_votes": 129, "rep_votes": 98, "other_votes": 0, "winner_candidate": "Mary Frances Williams", "winner_party": "UNK", "winner_votes": 129, "margin_votes": 31}, "1306700MR4B": {"total_votes": 1240, "dem_votes": 668, "rep_votes": 572, "other_votes": 0, "winner_candidate": "Mary Frances Williams", "winner_party": "UNK", "winner_votes": 668, "margin_votes": 96}, "1306700EP01": {"total_votes": 1373, "dem_votes": 796, "rep_votes": 577, "other_votes": 0, "winner_candidate": "Mary Frances Williams", "winner_party": "UNK", "winner_votes": 796, "margin_votes": 219}}}