{"office": "State House", "district": "145.0", "level": "vtd20", "keys": "Join on VTD20 GEOID20 (state+county+vtd id). Built by matching precinct names to VTD20 join keys; optionally uses --vtd20-crosswalk and --vtd20-supplemental-keymap.", "results": {"13021000WA2": {"total_votes": 387, "dem_votes": 0, "rep_votes": 387, "other_votes": 0, "winner_candidate": "Robert Dickey", "winner_party": "UNK", "winner_votes": 387, "margin_votes": 387}, "13021000WA1": {"total_votes": 1381, "dem_votes": 0, "rep_votes": 1381, "other_votes": 0, "winner_candidate": "Robert Dickey", "winner_party": "UNK", "winner_votes": 1381, "margin_votes": 1381}, "132250000B1": {"total_votes": 1434, "dem_votes": 0, "rep_votes": 1434, "other_votes": 0, "winner_candidate": "Robert Dickey", "winner_party": "UNK", "winner_votes": 1434, "margin_votes": 1434}, "132250000P1": {"total_votes": 750, "dem_votes": 0, "rep_votes": 750, "other_votes": 0, "winner_candidate": "Robert Dickey", "winner_party": "UNK", "winner_votes": 750, "margin_votes": 750}, "132250000B2": {"total_votes": 2453, "dem_votes": 0, "rep_votes": 2453, "other_votes": 0, "winner_candidate": "Robert Dickey", "winner_party": "UNK", "winner_votes": 2453, "margin_votes": 2453}, "132250000C1": {"total_votes": 536, "dem_votes": 0, "rep_votes": 536, "other_votes": 0, "winner_candidate": "Robert Dickey", "winner_party": "UNK", "winner_votes": 536, "margin_votes": 536}, "13207000014": {"total_votes": 310, "dem_votes": 0, "rep_votes": 310, "other_votes": 0, "winner_candidate": "Robert Dickey", "winner_party": "UNK", "winner_votes": 310, "margin_votes": 310}, "13207000006": {"total_votes": 272, "dem_votes": 0, "rep_votes": 272, "other_votes": 0, "winner_candidate": "Robert Dickey", "winner_party": "UNK", "winner_votes": 272, "margin_votes": 272}, "13153000VHS": {"total_votes": 1819, "dem_votes": 0, "rep_votes": 1819, "other_votes": 0, "winner_candidate": "Shaw Blackmon", "winner_party": "UNK", "winner_votes": 1819, "margin_votes": 1819}, "1315300CGTC": {"total_votes": 1968, "dem_votes": 0, "rep_votes": 1968, "other_votes": 0, "winner_candidate": "Shaw Blackmon", "winner_party": "UNK", "winner_votes": 1968, "margin_votes": 1968}, "1315300ROZR": {"total_votes": 3337, "dem_votes": 0, "rep_votes": 3337, "other_votes": 0, "winner_candidate": "Shaw Blackmon", "winner_party": "UNK", "winner_votes": 3337, "margin_votes": 3337}, "1315300MCMS": {"total_votes": 1301, "dem_votes": 0, "rep_votes": 1301, "other_votes": 0, "winner_candidate": "Shaw Blackmon", "winner_party": "UNK", "winner_votes": 1301, "margin_votes": 1301}, "13153000BMS": {"total_votes": 4263, "dem_votes": 0, "rep_votes": 4263, "other_votes": 0, "winner_candidate": "Shaw Blackmon", "winner_party": "UNK", "winner_votes": 4263, "margin_votes": 4263}, "1315300TWPK": {"total_votes": 1529, "dem_votes": 0, "rep_votes": 1529, "other_votes": 0, "winner_candidate": "Shaw Blackmon", "winner_party": "UNK", "winner_votes": 1529, "margin_votes": 1529}, "1315300FMMS": {"total_votes": 1739, "dem_votes": 0, "rep_votes": 1739, "other_votes": 0, "winner_candidate": "Shaw Blackmon", "winner_party": "UNK", "winner_votes": 1739, "margin_votes": 1739}, "1315300CENT": {"total_votes": 16, "dem_votes": 0, "rep_votes": 16, "other_votes": 0, "winner_candidate": "Robert Dickey", "winner_party": "UNK", "winner_votes": 16, "margin_votes": 16}, "1315300HHPC": {"total_votes": 1535, "dem_votes": 0, "rep_votes": 1535, "other_votes": 0, "winner_candidate": "Robert Dickey", "winner_party": "UNK", "winner_votes": 1535, "margin_votes": 1535}}}