{"office": "State Senate", "district": "1.0", "level": "vtd20", "keys": "Join on VTD20 GEOID20 (state+county+vtd id). Built by matching precinct names to VTD20 join keys; optionally uses --vtd20-crosswalk and --vtd20-supplemental-keymap.", "results": {"13029000003": {"total_votes": 778, "dem_votes": 172, "rep_votes": 606, "other_votes": 0, "winner_candidate": "Ben Watson", "winner_party": "UNK", "winner_votes": 606, "margin_votes": 434}, "13029000010": {"total_votes": 1229, "dem_votes": 290, "rep_votes": 939, "other_votes": 0, "winner_candidate": "Ben Watson", "winner_party": "UNK", "winner_votes": 939, "margin_votes": 649}, "13179000002": {"total_votes": 1477, "dem_votes": 842, "rep_votes": 635, "other_votes": 0, "winner_candidate": "James \"\"Jay\"\" Jones", "winner_party": "UNK", "winner_votes": 842, "margin_votes": 207}, "13179000014": {"total_votes": 762, "dem_votes": 566, "rep_votes": 196, "other_votes": 0, "winner_candidate": "James \"\"Jay\"\" Jones", "winner_party": "UNK", "winner_votes": 566, "margin_votes": 370}, "13179000005": {"total_votes": 1315, "dem_votes": 421, "rep_votes": 894, "other_votes": 0, "winner_candidate": "Ben Watson", "winner_party": "UNK", "winner_votes": 894, "margin_votes": 473}, "13179000007": {"total_votes": 1273, "dem_votes": 603, "rep_votes": 670, "other_votes": 0, "winner_candidate": "Ben Watson", "winner_party": "UNK", "winner_votes": 670, "margin_votes": 67}, "13179000006": {"total_votes": 1315, "dem_votes": 421, "rep_votes": 894, "other_votes": 0, "winner_candidate": "Ben Watson", "winner_party": "UNK", "winner_votes": 894, "margin_votes": 473}, "13179000003": {"total_votes": 2695, "dem_votes": 1225, "rep_votes": 1470, "other_votes": 0, "winner_candidate": "Ben Watson", "winner_party": "UNK", "winner_votes": 1470, "margin_votes": 245}}}