{
  "meta": {
    "scope": "state_senate",
    "contest_type": "president",
    "year": 2024,
    "source": "derived_vtd20",
    "generated_at_utc": "2026-03-21T19:47:35.597535+00:00",
    "match_coverage_pct": 100.0,
    "total_input_votes": 4016113,
    "matched_input_votes": 4016113,
    "input_files": [
      "Data/derived_vtd20/2024/contests/vtd20/President.json"
    ]
  },
  "general": {
    "results": {
      "1": {
        "total_votes": 66966,
        "dem_votes": 29331,
        "rep_votes": 37258,
        "other_votes": 377,
        "dem_candidate": "",
        "rep_candidate": "",
        "winner": "Republican",
        "winner_party": "REP",
        "margin_pct": 11.837350297165726
      },
      "2": {
        "total_votes": 76529,
        "dem_votes": 54796,
        "rep_votes": 21127,
        "other_votes": 607,
        "dem_candidate": "",
        "rep_candidate": "",
        "winner": "Democratic",
        "winner_party": "DEM",
        "margin_pct": -43.99508682982922
      },
      "3": {
        "total_votes": 30610,
        "dem_votes": 6920,
        "rep_votes": 23574,
        "other_votes": 116,
        "dem_candidate": "",
        "rep_candidate": "",
        "winner": "Republican",
        "winner_party": "REP",
        "margin_pct": 54.40705651747795
      },
      "4": {
        "total_votes": 72200,
        "dem_votes": 22989,
        "rep_votes": 48855,
        "other_votes": 356,
        "dem_candidate": "",
        "rep_candidate": "",
        "winner": "Republican",
        "winner_party": "REP",
        "margin_pct": 35.825484764542935
      },
      "5": {
        "total_votes": 50428,
        "dem_votes": 33323,
        "rep_votes": 16471,
        "other_votes": 634,
        "dem_candidate": "",
        "rep_candidate": "",
        "winner": "Democratic",
        "winner_party": "DEM",
        "margin_pct": -33.41794241294519
      },
      "6": {
        "total_votes": 88406,
        "dem_votes": 54355,
        "rep_votes": 33108,
        "other_votes": 942,
        "dem_candidate": "",
        "rep_candidate": "",
        "winner": "Democratic",
        "winner_party": "DEM",
        "margin_pct": -24.033436644571633
      },
      "7": {
        "total_votes": 86819,
        "dem_votes": 48976,
        "rep_votes": 36626,
        "other_votes": 1216,
        "dem_candidate": "",
        "rep_candidate": "",
        "winner": "Democratic",
        "winner_party": "DEM",
        "margin_pct": -14.224996832490582
      },
      "8": {
        "total_votes": 32114,
        "dem_votes": 7844,
        "rep_votes": 24159,
        "other_votes": 111,
        "dem_candidate": "",
        "rep_candidate": "",
        "winner": "Republican",
        "winner_party": "REP",
        "margin_pct": 50.8033879304976
      },
      "9": {
        "total_votes": 89682,
        "dem_votes": 53386,
        "rep_votes": 34906,
        "other_votes": 1391,
        "dem_candidate": "",
        "rep_candidate": "",
        "winner": "Democratic",
        "winner_party": "DEM",
        "margin_pct": -20.60614170067572
      },
      "10": {
        "total_votes": 94162,
        "dem_votes": 74494,
        "rep_votes": 19058,
        "other_votes": 609,
        "dem_candidate": "",
        "rep_candidate": "",
        "winner": "Democratic",
        "winner_party": "DEM",
        "margin_pct": -58.87300609587732
      },
      "11": {
        "total_votes": 69722,
        "dem_votes": 22227,
        "rep_votes": 47288,
        "other_votes": 207,
        "dem_candidate": "",
        "rep_candidate": "",
        "winner": "Republican",
        "winner_party": "REP",
        "margin_pct": 35.944178308138035
      },
      "12": {
        "total_votes": 57421,
        "dem_votes": 30803,
        "rep_votes": 26440,
        "other_votes": 178,
        "dem_candidate": "",
        "rep_candidate": "",
        "winner": "Democratic",
        "winner_party": "DEM",
        "margin_pct": -7.598265442956411
      },
      "13": {
        "total_votes": 61605,
        "dem_votes": 17644,
        "rep_votes": 43782,
        "other_votes": 178,
        "dem_candidate": "",
        "rep_candidate": "",
        "winner": "Republican",
        "winner_party": "REP",
        "margin_pct": 42.42837432026621
      },
      "14": {
        "total_votes": 77995,
        "dem_votes": 45597,
        "rep_votes": 31454,
        "other_votes": 944,
        "dem_candidate": "",
        "rep_candidate": "",
        "winner": "Democratic",
        "winner_party": "DEM",
        "margin_pct": -18.13321366754279
      },
      "15": {
        "total_votes": 39257,
        "dem_votes": 24644,
        "rep_votes": 14447,
        "other_votes": 166,
        "dem_candidate": "",
        "rep_candidate": "",
        "winner": "Democratic",
        "winner_party": "DEM",
        "margin_pct": -25.974985352930684
      },
      "16": {
        "total_votes": 105035,
        "dem_votes": 38697,
        "rep_votes": 65637,
        "other_votes": 702,
        "dem_candidate": "",
        "rep_candidate": "",
        "winner": "Republican",
        "winner_party": "REP",
        "margin_pct": 25.64859332603418
      },
      "17": {
        "total_votes": 63740,
        "dem_votes": 30577,
        "rep_votes": 32778,
        "other_votes": 385,
        "dem_candidate": "",
        "rep_candidate": "",
        "winner": "Republican",
        "winner_party": "REP",
        "margin_pct": 3.4530906808911204
      },
      "18": {
        "total_votes": 96810,
        "dem_votes": 38159,
        "rep_votes": 58162,
        "other_votes": 489,
        "dem_candidate": "",
        "rep_candidate": "",
        "winner": "Republican",
        "winner_party": "REP",
        "margin_pct": 20.662121681644457
      },
      "19": {
        "total_votes": 64109,
        "dem_votes": 13891,
        "rep_votes": 50057,
        "other_votes": 162,
        "dem_candidate": "",
        "rep_candidate": "",
        "winner": "Republican",
        "winner_party": "REP",
        "margin_pct": 56.413296105071055
      },
      "20": {
        "total_votes": 78207,
        "dem_votes": 26234,
        "rep_votes": 51636,
        "other_votes": 338,
        "dem_candidate": "",
        "rep_candidate": "",
        "winner": "Republican",
        "winner_party": "REP",
        "margin_pct": 32.48046850026213
      },
      "21": {
        "total_votes": 80666,
        "dem_votes": 25510,
        "rep_votes": 54346,
        "other_votes": 810,
        "dem_candidate": "",
        "rep_candidate": "",
        "winner": "Republican",
        "winner_party": "REP",
        "margin_pct": 35.74740287109811
      },
      "22": {
        "total_votes": 71864,
        "dem_votes": 49823,
        "rep_votes": 21637,
        "other_votes": 404,
        "dem_candidate": "",
        "rep_candidate": "",
        "winner": "Democratic",
        "winner_party": "DEM",
        "margin_pct": -39.221306913057994
      },
      "23": {
        "total_votes": 57209,
        "dem_votes": 22419,
        "rep_votes": 34572,
        "other_votes": 218,
        "dem_candidate": "",
        "rep_candidate": "",
        "winner": "Republican",
        "winner_party": "REP",
        "margin_pct": 21.243161041094933
      },
      "24": {
        "total_votes": 89665,
        "dem_votes": 27192,
        "rep_votes": 61938,
        "other_votes": 535,
        "dem_candidate": "",
        "rep_candidate": "",
        "winner": "Republican",
        "winner_party": "REP",
        "margin_pct": 38.750906150671945
      },
      "25": {
        "total_votes": 86315,
        "dem_votes": 36646,
        "rep_votes": 49279,
        "other_votes": 389,
        "dem_candidate": "",
        "rep_candidate": "",
        "winner": "Republican",
        "winner_party": "REP",
        "margin_pct": 14.63592654810867
      },
      "26": {
        "total_votes": 63072,
        "dem_votes": 39435,
        "rep_votes": 23410,
        "other_votes": 227,
        "dem_candidate": "",
        "rep_candidate": "",
        "winner": "Democratic",
        "winner_party": "DEM",
        "margin_pct": -25.407470826991375
      },
      "27": {
        "total_votes": 58793,
        "dem_votes": 17291,
        "rep_votes": 40925,
        "other_votes": 576,
        "dem_candidate": "",
        "rep_candidate": "",
        "winner": "Republican",
        "winner_party": "REP",
        "margin_pct": 40.1986631061521
      },
      "28": {
        "total_votes": 81536,
        "dem_votes": 24472,
        "rep_votes": 56508,
        "other_votes": 555,
        "dem_candidate": "",
        "rep_candidate": "",
        "winner": "Republican",
        "winner_party": "REP",
        "margin_pct": 39.290620094191524
      },
      "29": {
        "total_votes": 50685,
        "dem_votes": 15560,
        "rep_votes": 34906,
        "other_votes": 219,
        "dem_candidate": "",
        "rep_candidate": "",
        "winner": "Republican",
        "winner_party": "REP",
        "margin_pct": 38.169083555292495
      },
      "30": {
        "total_votes": 44918,
        "dem_votes": 12499,
        "rep_votes": 32213,
        "other_votes": 206,
        "dem_candidate": "",
        "rep_candidate": "",
        "winner": "Republican",
        "winner_party": "REP",
        "margin_pct": 43.88886415245559
      },
      "31": {
        "total_votes": 17308,
        "dem_votes": 3331,
        "rep_votes": 13910,
        "other_votes": 67,
        "dem_candidate": "",
        "rep_candidate": "",
        "winner": "Republican",
        "winner_party": "REP",
        "margin_pct": 61.12202449734227
      },
      "32": {
        "total_votes": 96468,
        "dem_votes": 41360,
        "rep_votes": 54045,
        "other_votes": 1063,
        "dem_candidate": "",
        "rep_candidate": "",
        "winner": "Republican",
        "winner_party": "REP",
        "margin_pct": 13.149438155657837
      },
      "33": {
        "total_votes": 64953,
        "dem_votes": 45146,
        "rep_votes": 19233,
        "other_votes": 575,
        "dem_candidate": "",
        "rep_candidate": "",
        "winner": "Democratic",
        "winner_party": "DEM",
        "margin_pct": -39.8950010007236
      },
      "34": {
        "total_votes": 66157,
        "dem_votes": 53476,
        "rep_votes": 12237,
        "other_votes": 444,
        "dem_candidate": "",
        "rep_candidate": "",
        "winner": "Democratic",
        "winner_party": "DEM",
        "margin_pct": -62.3350514684765
      },
      "35": {
        "total_votes": 51455,
        "dem_votes": 42891,
        "rep_votes": 8233,
        "other_votes": 331,
        "dem_candidate": "",
        "rep_candidate": "",
        "winner": "Democratic",
        "winner_party": "DEM",
        "margin_pct": -67.35594208531727
      },
      "36": {
        "total_votes": 82052,
        "dem_votes": 72308,
        "rep_votes": 8848,
        "other_votes": 896,
        "dem_candidate": "",
        "rep_candidate": "",
        "winner": "Democratic",
        "winner_party": "DEM",
        "margin_pct": -77.34119826451519
      },
      "37": {
        "total_votes": 113742,
        "dem_votes": 51440,
        "rep_votes": 61153,
        "other_votes": 1149,
        "dem_candidate": "",
        "rep_candidate": "",
        "winner": "Republican",
        "winner_party": "REP",
        "margin_pct": 8.53950167923898
      },
      "38": {
        "total_votes": 68147,
        "dem_votes": 54694,
        "rep_votes": 12898,
        "other_votes": 555,
        "dem_candidate": "",
        "rep_candidate": "",
        "winner": "Democratic",
        "winner_party": "DEM",
        "margin_pct": -61.33212026941758
      },
      "39": {
        "total_votes": 76932,
        "dem_votes": 66484,
        "rep_votes": 9757,
        "other_votes": 690,
        "dem_candidate": "",
        "rep_candidate": "",
        "winner": "Democratic",
        "winner_party": "DEM",
        "margin_pct": -73.73654656059897
      },
      "40": {
        "total_votes": 26393,
        "dem_votes": 17932,
        "rep_votes": 8106,
        "other_votes": 355,
        "dem_candidate": "",
        "rep_candidate": "",
        "winner": "Democratic",
        "winner_party": "DEM",
        "margin_pct": -37.22956844617891
      },
      "41": {
        "total_votes": 53896,
        "dem_votes": 43960,
        "rep_votes": 9391,
        "other_votes": 545,
        "dem_candidate": "",
        "rep_candidate": "",
        "winner": "Democratic",
        "winner_party": "DEM",
        "margin_pct": -64.14019593290782
      },
      "42": {
        "total_votes": 52709,
        "dem_votes": 43349,
        "rep_votes": 8739,
        "other_votes": 621,
        "dem_candidate": "",
        "rep_candidate": "",
        "winner": "Democratic",
        "winner_party": "DEM",
        "margin_pct": -65.66241059401621
      },
      "43": {
        "total_votes": 17286,
        "dem_votes": 14799,
        "rep_votes": 2401,
        "other_votes": 86,
        "dem_candidate": "",
        "rep_candidate": "",
        "winner": "Democratic",
        "winner_party": "DEM",
        "margin_pct": -71.72278144162907
      },
      "44": {
        "total_votes": 64675,
        "dem_votes": 54867,
        "rep_votes": 9378,
        "other_votes": 429,
        "dem_candidate": "",
        "rep_candidate": "",
        "winner": "Democratic",
        "winner_party": "DEM",
        "margin_pct": -70.33475067645922
      },
      "45": {
        "total_votes": 98714,
        "dem_votes": 41742,
        "rep_votes": 56068,
        "other_votes": 904,
        "dem_candidate": "",
        "rep_candidate": "",
        "winner": "Republican",
        "winner_party": "REP",
        "margin_pct": 14.512632453350083
      },
      "46": {
        "total_votes": 93023,
        "dem_votes": 37154,
        "rep_votes": 55086,
        "other_votes": 783,
        "dem_candidate": "",
        "rep_candidate": "",
        "winner": "Republican",
        "winner_party": "REP",
        "margin_pct": 19.276953011620783
      },
      "47": {
        "total_votes": 100185,
        "dem_votes": 38050,
        "rep_votes": 61458,
        "other_votes": 677,
        "dem_candidate": "",
        "rep_candidate": "",
        "winner": "Republican",
        "winner_party": "REP",
        "margin_pct": 23.364775165943005
      },
      "48": {
        "total_votes": 79200,
        "dem_votes": 37959,
        "rep_votes": 40200,
        "other_votes": 1042,
        "dem_candidate": "",
        "rep_candidate": "",
        "winner": "Republican",
        "winner_party": "REP",
        "margin_pct": 2.8295454545454546
      },
      "49": {
        "total_votes": 96855,
        "dem_votes": 26670,
        "rep_votes": 69575,
        "other_votes": 610,
        "dem_candidate": "",
        "rep_candidate": "",
        "winner": "Republican",
        "winner_party": "REP",
        "margin_pct": 44.29817768829694
      },
      "50": {
        "total_votes": 87138,
        "dem_votes": 15336,
        "rep_votes": 71452,
        "other_votes": 350,
        "dem_candidate": "",
        "rep_candidate": "",
        "winner": "Republican",
        "winner_party": "REP",
        "margin_pct": 64.39899928848493
      },
      "51": {
        "total_votes": 111539,
        "dem_votes": 19639,
        "rep_votes": 91324,
        "other_votes": 576,
        "dem_candidate": "",
        "rep_candidate": "",
        "winner": "Republican",
        "winner_party": "REP",
        "margin_pct": 64.26900008068927
      },
      "52": {
        "total_votes": 77294,
        "dem_votes": 20640,
        "rep_votes": 56206,
        "other_votes": 448,
        "dem_candidate": "",
        "rep_candidate": "",
        "winner": "Republican",
        "winner_party": "REP",
        "margin_pct": 46.013920873547754
      },
      "53": {
        "total_votes": 82835,
        "dem_votes": 17827,
        "rep_votes": 64544,
        "other_votes": 464,
        "dem_candidate": "",
        "rep_candidate": "",
        "winner": "Republican",
        "winner_party": "REP",
        "margin_pct": 56.39765799480896
      },
      "54": {
        "total_votes": 48423,
        "dem_votes": 10561,
        "rep_votes": 37639,
        "other_votes": 222,
        "dem_candidate": "",
        "rep_candidate": "",
        "winner": "Republican",
        "winner_party": "REP",
        "margin_pct": 55.919707576977885
      },
      "55": {
        "total_votes": 95500,
        "dem_votes": 74435,
        "rep_votes": 20295,
        "other_votes": 770,
        "dem_candidate": "",
        "rep_candidate": "",
        "winner": "Democratic",
        "winner_party": "DEM",
        "margin_pct": -56.69109947643979
      },
      "56": {
        "total_votes": 106694,
        "dem_votes": 46212,
        "rep_votes": 59264,
        "other_votes": 1218,
        "dem_candidate": "",
        "rep_candidate": "",
        "winner": "Republican",
        "winner_party": "REP",
        "margin_pct": 12.233115264213545
      }
    }
  }
}