{
  "meta": {
    "scope": "state_senate",
    "contest_type": "attorney_general",
    "year": 2018,
    "source": "derived_vtd20",
    "generated_at_utc": "2026-03-21T18:35:12.814004+00:00",
    "match_coverage_pct": 100.0,
    "total_input_votes": 3398942,
    "matched_input_votes": 3398942,
    "input_files": [
      "Data/derived_vtd20/2018/contests/vtd20/Attorney_General.json"
    ]
  },
  "general": {
    "results": {
      "1": {
        "total_votes": 28061,
        "dem_votes": 12693,
        "rep_votes": 0,
        "other_votes": 15368,
        "dem_candidate": "",
        "rep_candidate": "",
        "winner": "Other",
        "winner_party": "OTH",
        "margin_pct": -45.233598232422224
      },
      "2": {
        "total_votes": 2142,
        "dem_votes": 1226,
        "rep_votes": 0,
        "other_votes": 916,
        "dem_candidate": "",
        "rep_candidate": "",
        "winner": "Democratic",
        "winner_party": "DEM",
        "margin_pct": -57.236227824463114
      },
      "3": {
        "total_votes": 53515,
        "dem_votes": 16822,
        "rep_votes": 0,
        "other_votes": 36694,
        "dem_candidate": "",
        "rep_candidate": "",
        "winner": "Other",
        "winner_party": "OTH",
        "margin_pct": -31.434177333457907
      },
      "4": {
        "total_votes": 49397,
        "dem_votes": 14609,
        "rep_votes": 0,
        "other_votes": 34788,
        "dem_candidate": "",
        "rep_candidate": "",
        "winner": "Other",
        "winner_party": "OTH",
        "margin_pct": -29.574670526550197
      },
      "5": {
        "total_votes": 38861,
        "dem_votes": 29793,
        "rep_votes": 0,
        "other_votes": 9068,
        "dem_candidate": "",
        "rep_candidate": "",
        "winner": "Democratic",
        "winner_party": "DEM",
        "margin_pct": -76.66555158127686
      },
      "6": {
        "total_votes": 79031,
        "dem_votes": 43098,
        "rep_votes": 0,
        "other_votes": 35933,
        "dem_candidate": "",
        "rep_candidate": "",
        "winner": "Democratic",
        "winner_party": "DEM",
        "margin_pct": -54.533031342131565
      },
      "7": {
        "total_votes": 64297,
        "dem_votes": 35211,
        "rep_votes": 0,
        "other_votes": 29085,
        "dem_candidate": "",
        "rep_candidate": "",
        "winner": "Democratic",
        "winner_party": "DEM",
        "margin_pct": -54.763052708524505
      },
      "8": {
        "total_votes": 55688,
        "dem_votes": 18762,
        "rep_votes": 0,
        "other_votes": 36925,
        "dem_candidate": "",
        "rep_candidate": "",
        "winner": "Other",
        "winner_party": "OTH",
        "margin_pct": -33.6912799885074
      },
      "9": {
        "total_votes": 67645,
        "dem_votes": 38110,
        "rep_votes": 0,
        "other_votes": 29534,
        "dem_candidate": "",
        "rep_candidate": "",
        "winner": "Democratic",
        "winner_party": "DEM",
        "margin_pct": -56.33823638110725
      },
      "10": {
        "total_votes": 79781,
        "dem_votes": 63255,
        "rep_votes": 0,
        "other_votes": 16525,
        "dem_candidate": "",
        "rep_candidate": "",
        "winner": "Democratic",
        "winner_party": "DEM",
        "margin_pct": -79.28579486343867
      },
      "11": {
        "total_votes": 54160,
        "dem_votes": 17713,
        "rep_votes": 0,
        "other_votes": 36447,
        "dem_candidate": "",
        "rep_candidate": "",
        "winner": "Other",
        "winner_party": "OTH",
        "margin_pct": -32.704948301329395
      },
      "12": {
        "total_votes": 57664,
        "dem_votes": 32137,
        "rep_votes": 0,
        "other_votes": 25527,
        "dem_candidate": "",
        "rep_candidate": "",
        "winner": "Democratic",
        "winner_party": "DEM",
        "margin_pct": -55.731478912319645
      },
      "13": {
        "total_votes": 56664,
        "dem_votes": 16176,
        "rep_votes": 0,
        "other_votes": 40488,
        "dem_candidate": "",
        "rep_candidate": "",
        "winner": "Other",
        "winner_party": "OTH",
        "margin_pct": -28.547225751800088
      },
      "14": {
        "total_votes": 75980,
        "dem_votes": 40970,
        "rep_votes": 0,
        "other_votes": 35010,
        "dem_candidate": "",
        "rep_candidate": "",
        "winner": "Democratic",
        "winner_party": "DEM",
        "margin_pct": -53.92208475914715
      },
      "15": {
        "total_votes": 47522,
        "dem_votes": 33521,
        "rep_votes": 0,
        "other_votes": 14001,
        "dem_candidate": "",
        "rep_candidate": "",
        "winner": "Democratic",
        "winner_party": "DEM",
        "margin_pct": -70.5378561508354
      },
      "16": {
        "total_votes": 71832,
        "dem_votes": 23737,
        "rep_votes": 0,
        "other_votes": 48095,
        "dem_candidate": "",
        "rep_candidate": "",
        "winner": "Other",
        "winner_party": "OTH",
        "margin_pct": -33.04516093106137
      },
      "17": {
        "total_votes": 77755,
        "dem_votes": 28522,
        "rep_votes": 0,
        "other_votes": 49233,
        "dem_candidate": "",
        "rep_candidate": "",
        "winner": "Other",
        "winner_party": "OTH",
        "margin_pct": -36.68188540929844
      },
      "18": {
        "total_votes": 77449,
        "dem_votes": 29289,
        "rep_votes": 0,
        "other_votes": 48160,
        "dem_candidate": "",
        "rep_candidate": "",
        "winner": "Other",
        "winner_party": "OTH",
        "margin_pct": -37.81714418520575
      },
      "19": {
        "total_votes": 57940,
        "dem_votes": 14010,
        "rep_votes": 0,
        "other_votes": 43930,
        "dem_candidate": "",
        "rep_candidate": "",
        "winner": "Other",
        "winner_party": "OTH",
        "margin_pct": -24.18018639972385
      },
      "20": {
        "total_votes": 67128,
        "dem_votes": 21869,
        "rep_votes": 0,
        "other_votes": 45259,
        "dem_candidate": "",
        "rep_candidate": "",
        "winner": "Other",
        "winner_party": "OTH",
        "margin_pct": -32.57805982600405
      },
      "21": {
        "total_votes": 76758,
        "dem_votes": 22728,
        "rep_votes": 0,
        "other_votes": 54030,
        "dem_candidate": "",
        "rep_candidate": "",
        "winner": "Other",
        "winner_party": "OTH",
        "margin_pct": -29.60994293754397
      },
      "22": {
        "total_votes": 63599,
        "dem_votes": 44506,
        "rep_votes": 0,
        "other_votes": 19093,
        "dem_candidate": "",
        "rep_candidate": "",
        "winner": "Democratic",
        "winner_party": "DEM",
        "margin_pct": -69.97908772150505
      },
      "23": {
        "total_votes": 56401,
        "dem_votes": 23255,
        "rep_votes": 0,
        "other_votes": 33146,
        "dem_candidate": "",
        "rep_candidate": "",
        "winner": "Other",
        "winner_party": "OTH",
        "margin_pct": -41.231538447899865
      },
      "24": {
        "total_votes": 70013,
        "dem_votes": 20346,
        "rep_votes": 0,
        "other_votes": 49667,
        "dem_candidate": "",
        "rep_candidate": "",
        "winner": "Other",
        "winner_party": "OTH",
        "margin_pct": -29.060317369631356
      },
      "25": {
        "total_votes": 62139,
        "dem_votes": 25279,
        "rep_votes": 0,
        "other_votes": 36860,
        "dem_candidate": "",
        "rep_candidate": "",
        "winner": "Other",
        "winner_party": "OTH",
        "margin_pct": -40.68137562561354
      },
      "26": {
        "total_votes": 63073,
        "dem_votes": 40682,
        "rep_votes": 0,
        "other_votes": 22391,
        "dem_candidate": "",
        "rep_candidate": "",
        "winner": "Democratic",
        "winner_party": "DEM",
        "margin_pct": -64.49986523552074
      },
      "27": {
        "total_votes": 70383,
        "dem_votes": 18208,
        "rep_votes": 0,
        "other_votes": 52174,
        "dem_candidate": "",
        "rep_candidate": "",
        "winner": "Other",
        "winner_party": "OTH",
        "margin_pct": -25.8698833525141
      },
      "28": {
        "total_votes": 70899,
        "dem_votes": 21589,
        "rep_votes": 0,
        "other_votes": 49310,
        "dem_candidate": "",
        "rep_candidate": "",
        "winner": "Other",
        "winner_party": "OTH",
        "margin_pct": -30.45035896133937
      },
      "29": {
        "total_votes": 64958,
        "dem_votes": 23738,
        "rep_votes": 0,
        "other_votes": 41220,
        "dem_candidate": "",
        "rep_candidate": "",
        "winner": "Other",
        "winner_party": "OTH",
        "margin_pct": -36.54361279596047
      },
      "30": {
        "total_votes": 26119,
        "dem_votes": 8692,
        "rep_votes": 0,
        "other_votes": 17427,
        "dem_candidate": "",
        "rep_candidate": "",
        "winner": "Other",
        "winner_party": "OTH",
        "margin_pct": -33.27845629618286
      },
      "31": {
        "total_votes": 47651,
        "dem_votes": 14640,
        "rep_votes": 0,
        "other_votes": 33011,
        "dem_candidate": "",
        "rep_candidate": "",
        "winner": "Other",
        "winner_party": "OTH",
        "margin_pct": -30.72338460892741
      },
      "32": {
        "total_votes": 76221,
        "dem_votes": 30300,
        "rep_votes": 0,
        "other_votes": 45921,
        "dem_candidate": "",
        "rep_candidate": "",
        "winner": "Other",
        "winner_party": "OTH",
        "margin_pct": -39.75282402487503
      },
      "33": {
        "total_votes": 62347,
        "dem_votes": 44127,
        "rep_votes": 0,
        "other_votes": 18221,
        "dem_candidate": "",
        "rep_candidate": "",
        "winner": "Democratic",
        "winner_party": "DEM",
        "margin_pct": -70.7764607759796
      },
      "34": {
        "total_votes": 59301,
        "dem_votes": 49661,
        "rep_votes": 0,
        "other_votes": 9640,
        "dem_candidate": "",
        "rep_candidate": "",
        "winner": "Democratic",
        "winner_party": "DEM",
        "margin_pct": -83.74395035496872
      },
      "35": {
        "total_votes": 71451,
        "dem_votes": 57659,
        "rep_votes": 0,
        "other_votes": 13792,
        "dem_candidate": "",
        "rep_candidate": "",
        "winner": "Democratic",
        "winner_party": "DEM",
        "margin_pct": -80.69726106002715
      },
      "36": {
        "total_votes": 71747,
        "dem_votes": 63685,
        "rep_votes": 0,
        "other_votes": 8063,
        "dem_candidate": "",
        "rep_candidate": "",
        "winner": "Democratic",
        "winner_party": "DEM",
        "margin_pct": -88.7632932387417
      },
      "37": {
        "total_votes": 85205,
        "dem_votes": 34676,
        "rep_votes": 0,
        "other_votes": 50529,
        "dem_candidate": "",
        "rep_candidate": "",
        "winner": "Other",
        "winner_party": "OTH",
        "margin_pct": -40.697142186491405
      },
      "38": {
        "total_votes": 75159,
        "dem_votes": 61728,
        "rep_votes": 0,
        "other_votes": 13431,
        "dem_candidate": "",
        "rep_candidate": "",
        "winner": "Democratic",
        "winner_party": "DEM",
        "margin_pct": -82.12988464455354
      },
      "39": {
        "total_votes": 69443,
        "dem_votes": 60183,
        "rep_votes": 0,
        "other_votes": 9260,
        "dem_candidate": "",
        "rep_candidate": "",
        "winner": "Democratic",
        "winner_party": "DEM",
        "margin_pct": -86.66532263871089
      },
      "40": {
        "total_votes": 47383,
        "dem_votes": 28555,
        "rep_votes": 0,
        "other_votes": 18827,
        "dem_candidate": "",
        "rep_candidate": "",
        "winner": "Democratic",
        "winner_party": "DEM",
        "margin_pct": -60.264229787054425
      },
      "41": {
        "total_votes": 63787,
        "dem_votes": 52290,
        "rep_votes": 0,
        "other_votes": 11498,
        "dem_candidate": "",
        "rep_candidate": "",
        "winner": "Democratic",
        "winner_party": "DEM",
        "margin_pct": -81.97595121262952
      },
      "42": {
        "total_votes": 56329,
        "dem_votes": 44817,
        "rep_votes": 0,
        "other_votes": 11512,
        "dem_candidate": "",
        "rep_candidate": "",
        "winner": "Democratic",
        "winner_party": "DEM",
        "margin_pct": -79.56292495872464
      },
      "43": {
        "total_votes": 70840,
        "dem_votes": 50766,
        "rep_votes": 0,
        "other_votes": 20074,
        "dem_candidate": "",
        "rep_candidate": "",
        "winner": "Democratic",
        "winner_party": "DEM",
        "margin_pct": -71.66290231507622
      },
      "44": {
        "total_votes": 66998,
        "dem_votes": 58712,
        "rep_votes": 0,
        "other_votes": 8286,
        "dem_candidate": "",
        "rep_candidate": "",
        "winner": "Democratic",
        "winner_party": "DEM",
        "margin_pct": -87.63246664079524
      },
      "45": {
        "total_votes": 52841,
        "dem_votes": 21136,
        "rep_votes": 0,
        "other_votes": 31705,
        "dem_candidate": "",
        "rep_candidate": "",
        "winner": "Other",
        "winner_party": "OTH",
        "margin_pct": -39.99924301205503
      },
      "46": {
        "total_votes": 58411,
        "dem_votes": 20192,
        "rep_votes": 0,
        "other_votes": 38219,
        "dem_candidate": "",
        "rep_candidate": "",
        "winner": "Other",
        "winner_party": "OTH",
        "margin_pct": -34.568831213298864
      },
      "47": {
        "total_votes": 40226,
        "dem_votes": 12365,
        "rep_votes": 0,
        "other_votes": 27861,
        "dem_candidate": "",
        "rep_candidate": "",
        "winner": "Other",
        "winner_party": "OTH",
        "margin_pct": -30.738825635161337
      },
      "48": {
        "total_votes": 71138,
        "dem_votes": 29847,
        "rep_votes": 0,
        "other_votes": 41291,
        "dem_candidate": "",
        "rep_candidate": "",
        "winner": "Other",
        "winner_party": "OTH",
        "margin_pct": -41.95647895639461
      },
      "49": {
        "total_votes": 10945,
        "dem_votes": 4293,
        "rep_votes": 0,
        "other_votes": 6652,
        "dem_candidate": "",
        "rep_candidate": "",
        "winner": "Other",
        "winner_party": "OTH",
        "margin_pct": -39.223389675650985
      },
      "50": {
        "total_votes": 44913,
        "dem_votes": 7356,
        "rep_votes": 0,
        "other_votes": 37557,
        "dem_candidate": "",
        "rep_candidate": "",
        "winner": "Other",
        "winner_party": "OTH",
        "margin_pct": -16.37833144078552
      },
      "51": {
        "total_votes": 76237,
        "dem_votes": 12945,
        "rep_votes": 0,
        "other_votes": 63292,
        "dem_candidate": "",
        "rep_candidate": "",
        "winner": "Other",
        "winner_party": "OTH",
        "margin_pct": -16.979944121620736
      },
      "52": {
        "total_votes": 62376,
        "dem_votes": 16352,
        "rep_votes": 0,
        "other_votes": 46024,
        "dem_candidate": "",
        "rep_candidate": "",
        "winner": "Other",
        "winner_party": "OTH",
        "margin_pct": -26.215210978581503
      },
      "53": {
        "total_votes": 54691,
        "dem_votes": 10817,
        "rep_votes": 0,
        "other_votes": 43874,
        "dem_candidate": "",
        "rep_candidate": "",
        "winner": "Other",
        "winner_party": "OTH",
        "margin_pct": -19.77839132581229
      },
      "54": {
        "total_votes": 51902,
        "dem_votes": 11680,
        "rep_votes": 0,
        "other_votes": 40222,
        "dem_candidate": "",
        "rep_candidate": "",
        "winner": "Other",
        "winner_party": "OTH",
        "margin_pct": -22.503949751454662
      },
      "55": {
        "total_votes": 75943,
        "dem_votes": 59599,
        "rep_votes": 0,
        "other_votes": 16344,
        "dem_candidate": "",
        "rep_candidate": "",
        "winner": "Democratic",
        "winner_party": "DEM",
        "margin_pct": -78.47859578894698
      },
      "56": {
        "total_votes": 88603,
        "dem_votes": 33805,
        "rep_votes": 0,
        "other_votes": 54798,
        "dem_candidate": "",
        "rep_candidate": "",
        "winner": "Other",
        "winner_party": "OTH",
        "margin_pct": -38.15333566583524
      }
    }
  }
}